<PAMDataset>
  <PAMRasterBand band="1">
    <Metadata>
      <MDI key="STATISTICS_COVARIANCES">0.0001796685271231566</MDI>
      <MDI key="STATISTICS_EXCLUDEDVALUES"></MDI>
      <MDI key="STATISTICS_MAXIMUM">0.27445545818495</MDI>
      <MDI key="STATISTICS_MEAN">0.091800411828436</MDI>
      <MDI key="STATISTICS_MINIMUM">0.05258209260039</MDI>
      <MDI key="STATISTICS_SKIPFACTORX">1</MDI>
      <MDI key="STATISTICS_SKIPFACTORY">1</MDI>
      <MDI key="STATISTICS_STDDEV">0.013404048907817</MDI>
    </Metadata>
  </PAMRasterBand>
</PAMDataset>
