<PAMDataset>
  <PAMRasterBand band="1">
    <Metadata>
      <MDI key="STATISTICS_COVARIANCES">0.05344865566051249</MDI>
      <MDI key="STATISTICS_EXCLUDEDVALUES"></MDI>
      <MDI key="STATISTICS_MAXIMUM">6.6228346456693</MDI>
      <MDI key="STATISTICS_MEAN">5.6030442359378</MDI>
      <MDI key="STATISTICS_MINIMUM">5.2462598425197</MDI>
      <MDI key="STATISTICS_SKIPFACTORX">1</MDI>
      <MDI key="STATISTICS_SKIPFACTORY">1</MDI>
      <MDI key="STATISTICS_STDDEV">0.23118965301352</MDI>
    </Metadata>
  </PAMRasterBand>
</PAMDataset>
