<PAMDataset>
  <PAMRasterBand band="1">
    <Metadata>
      <MDI key="STATISTICS_COVARIANCES">1367.756721933951</MDI>
      <MDI key="STATISTICS_EXCLUDEDVALUES"></MDI>
      <MDI key="STATISTICS_MAXIMUM">241.1</MDI>
      <MDI key="STATISTICS_MEAN">135.45830810772</MDI>
      <MDI key="STATISTICS_MINIMUM">15.255118110236</MDI>
      <MDI key="STATISTICS_SKIPFACTORX">1</MDI>
      <MDI key="STATISTICS_SKIPFACTORY">1</MDI>
      <MDI key="STATISTICS_STDDEV">36.983195128787</MDI>
    </Metadata>
  </PAMRasterBand>
</PAMDataset>
